acoustotreams/__init__.py
acoustotreams/_coreacoustics.py
acoustotreams/_materialacoustics.py
acoustotreams/_operatorsacoustics.py
acoustotreams/_smatrixacoustics.py
acoustotreams/_tmatrixacoustics.py
acoustotreams/_wavesacoustics.py
acoustotreams/coeffs.py
acoustotreams/scw.py
acoustotreams/spw.py
acoustotreams/ssw.py
acoustotreams-0.1.44.dist-info/LICENSE
acoustotreams-0.1.44.dist-info/METADATA
acoustotreams-0.1.44.dist-info/WHEEL
acoustotreams-0.1.44.dist-info/top_level.txt
acoustotreams-0.1.44.dist-info/RECORD
