Metadata-Version: 2.2
Name: acoustotreams
Version: 0.1.44
Summary: A Python package for acoustic wave scattering based on the T-matrix method
Home-page: https://github.com/NikUstimenko/acoustotreams
Author: Nikita Ustimenko
Author-email: nikita.ustimenko@kit.edu
License: MIT
Project-URL: Bug Tracker, https://github.com/NikUstimenko/acoustotreams/issues
Classifier: Programming Language :: Python :: 3
Classifier: License :: OSI Approved :: MIT License
Classifier: Operating System :: OS Independent
Requires-Python: >=3.8
License-File: LICENSE
Requires-Dist: numpy
Requires-Dist: scipy
Requires-Dist: treams
Dynamic: author
Dynamic: author-email
Dynamic: classifier
Dynamic: description
Dynamic: description-content-type
Dynamic: home-page
Dynamic: license
Dynamic: project-url
Dynamic: requires-dist
Dynamic: requires-python
Dynamic: summary
